{
	"pages": [ //pages数组中第一项表示应用启动页，参考：https://uniapp.dcloud.io/collocation/pages
		{
			"path": "pages/index",
			"style": {
				"navigationBarTitleText": "首页"
			}
		},
		{
			"path" : "pages/menu",
			"style" : 
			{
				"navigationBarTitleText" : "菜单界面",
				"enablePullDownRefresh" : true
			}
		},
		{
			"path": "pages/special",
			"style": {
				"navigationBarTitleText": "特产页面",
				"enablePullDownRefresh": true
			}
		},
		{
			"path" : "pages/userPage",
			"style" : 
			{
				"navigationBarTitleText" : "用户页面",
				"enablePullDownRefresh" : false
			}
		}
	],
	"tabBar": {
	    "color": "#7f7f7f",
	    "selectedColor": "#1a7a6d",  // 和你原样式一致的颜色
	    "backgroundColor": "#ffffff",
	    "borderStyle": "white",
	    "list": [
	      {
	        "pagePath": "pages/index",
	        "text": "首页",
	        "iconPath": "static/tabs/home.png",
	        "selectedIconPath": "static/tabs/home-active.png"
	      },
	      {
	        "pagePath": "pages/postPage",
	        "text": "文字",
	        "iconPath": "static/tabs/post.png",
	        "selectedIconPath": "static/tabs/post-active.png"
	      },
	      {
	        "pagePath": "pages/demo1",
	        "text": "商城",
	        "iconPath": "static/tabs/mall.png",
	        "selectedIconPath": "static/tabs/mall-active.png"
	      },
	      {
	        "pagePath": "pages/userPage",
	        "text": "我的",
	        "iconPath": "static/tabs/user.png",
	        "selectedIconPath": "static/tabs/user-active.png"
	      }
	    ]
	  },
	"globalStyle": {
		"navigationBarTextStyle": "black",
		"navigationBarTitleText": "东江鱼庄", 
		"navigationBarBackgroundColor": "#ffffff",
		"backgroundColor": "#f5f9f8"
	},
	"uniIdRouter": {}
}
